{"code":0,"message":"操作成功","data":{"lastTimestamp":1637402805515,"ridingOrders":[{"bizId":1,"orderId":"17636634531639613720208","bikeId":"8653908341","startTimestamp":1639613721000,"endTimestamp":1639614024000,"distanceMeter":750,"payStatus":1,"showRidingStatus":0,"originFeeCent":150,"actualFeeCent":0,"carbonEmissionsGram":36.5,"discountDesc":"骑行卡抵扣1.5元","penaltyDesc":[]},{"bizId":1,"orderId":"17636634531639563015077","bikeId":"8653908341","startTimestamp":1639563017000,"endTimestamp":1639563362000,"distanceMeter":750,"payStatus":1,"showRidingStatus":0,"originFeeCent":150,"actualFeeCent":0,"carbonEmissionsGram":36.5,"discountDesc":"骑行卡抵扣1.5元","penaltyDesc":[]},{"bizId":1,"orderId":"17636634531639527233504","bikeId":"8651694635","startTimestamp":1639527235000,"endTimestamp":1639527568000,"distanceMeter":750,"payStatus":1,"showRidingStatus":0,"originFeeCent":150,"actualFeeCent":0,"carbonEmissionsGram":36.5,"discountDesc":"优惠抵扣1.5元","penaltyDesc":[]},{"bizId":1,"orderId":"17636634531639473711596","bikeId":"8651694635","startTimestamp":1639473713000,"endTimestamp":1639474218000,"distanceMeter":1200,"payStatus":1,"showRidingStatus":0,"originFeeCent":150,"actualFeeCent":0,"carbonEmissionsGram":58.4,"discountDesc":"骑行卡抵扣1.5元","penaltyDesc":[]},{"bizId":1,"orderId":"17636634531639473693077","bikeId":"8640131706","startTimestamp":1639473693000,"endTimestamp":1639473701000,"distanceMeter":0,"payStatus":1,"showRidingStatus":0,"originFeeCent":0,"actualFeeCent":0,"carbonEmissionsGram":0.0,"discountDesc":null,"penaltyDesc":[]},{"bizId":2,"orderId":"17636634531637578858742","bikeId":"8661406461","startTimestamp":1637578895000,"endTimestamp":1637580763914,"distanceMeter":6360,"payStatus":1,"showRidingStatus":0,"originFeeCent":400,"actualFeeCent":150,"carbonEmissionsGram":346.6,"discountDesc":"骑行卡抵扣2.5元","penaltyDesc":[]},{"bizId":1,"orderId":"17636634531637578760341","bikeId":"8641010935","startTimestamp":1637578762000,"endTimestamp":1637578841000,"distanceMeter":150,"payStatus":1,"showRidingStatus":0,"originFeeCent":150,"actualFeeCent":0,"carbonEmissionsGram":7.3,"discountDesc":"骑行卡抵扣1.5元","penaltyDesc":[]},{"bizId":1,"orderId":"17636634531637575797321","bikeId":"8641010935","startTimestamp":1637575799000,"endTimestamp":1637576215000,"distanceMeter":900,"payStatus":1,"showRidingStatus":0,"originFeeCent":150,"actualFeeCent":0,"carbonEmissionsGram":43.8,"discountDesc":"骑行卡抵扣1.5元","penaltyDesc":[]},{"bizId":1,"orderId":"17636634531637540156701","bikeId":"8640999063","startTimestamp":1637540158000,"endTimestamp":1637540472000,"distanceMeter":750,"payStatus":1,"showRidingStatus":0,"originFeeCent":150,"actualFeeCent":0,"carbonEmissionsGram":36.5,"discountDesc":"骑行卡抵扣1.5元","penaltyDesc":[]},{"bizId":1,"orderId":"17636634531637402805510","bikeId":"8641749654","startTimestamp":1637402808000,"endTimestamp":1637403492000,"distanceMeter":1650,"payStatus":1,"showRidingStatus":0,"originFeeCent":150,"actualFeeCent":0,"carbonEmissionsGram":80.3,"discountDesc":"骑行卡抵扣1.5元","penaltyDesc":[]}]}}